qds_sdk/__init__.py
qds_sdk/account.py
qds_sdk/actions.py
qds_sdk/app.py
qds_sdk/cluster.py
qds_sdk/cluster_info_v22.py
qds_sdk/clusterv2.py
qds_sdk/cmd_line.py
qds_sdk/commands.py
qds_sdk/connection.py
qds_sdk/dbtaps.py
qds_sdk/engine.py
qds_sdk/exception.py
qds_sdk/group.py
qds_sdk/nezha.py
qds_sdk/pipelines.py
qds_sdk/qubole.py
qds_sdk/report.py
qds_sdk/resource.py
qds_sdk/role.py
qds_sdk/scheduler.py
qds_sdk/sensors.py
qds_sdk/template.py
qds_sdk/user.py
qds_sdk/util.py
qds_sdk/cloud/__init__.py
qds_sdk/cloud/aws_cloud.py
qds_sdk/cloud/azure_cloud.py
qds_sdk/cloud/cloud.py
qds_sdk/cloud/gcp_cloud.py
qds_sdk/cloud/oracle_bmc_cloud.py
qds_sdk/cloud/oracle_opc_cloud.py
qds_sdk-1.17.0.data/scripts/qds.py
qds_sdk-1.17.0.dist-info/LICENSE
qds_sdk-1.17.0.dist-info/METADATA
qds_sdk-1.17.0.dist-info/WHEEL
qds_sdk-1.17.0.dist-info/top_level.txt
qds_sdk-1.17.0.dist-info/RECORD
