Metadata-Version: 2.2
Name: qds_sdk
Version: 1.17.0
Summary: Python SDK for coding to the Qubole Data Service API
Home-page: https://github.com/qubole/qds-sdk-py
Author: Qubole
Author-email: dev@qubole.com
License: Apache License 2.0
Keywords: qubole sdk api
Classifier: Environment :: Console
Classifier: Intended Audience :: Developers
Classifier: License :: OSI Approved :: Apache Software License
Classifier: Programming Language :: Python
Classifier: Programming Language :: Python :: 2
Classifier: Programming Language :: Python :: 2.7
Classifier: Programming Language :: Python :: 3
Classifier: Programming Language :: Python :: 3.3
Classifier: Programming Language :: Python :: 3.4
Classifier: Programming Language :: Python :: 3.10
Classifier: Programming Language :: Python :: 3.11
Classifier: Programming Language :: Python :: 3.12
Requires-Python: >=2.7
License-File: LICENSE
Requires-Dist: requests>=2.21.0
Requires-Dist: boto3>=1.15.0
Requires-Dist: six>=1.12.0
Requires-Dist: urllib3>=1.24.3
Requires-Dist: inflection>=0.3.1
Dynamic: author
Dynamic: author-email
Dynamic: classifier
Dynamic: description
Dynamic: home-page
Dynamic: keywords
Dynamic: license
Dynamic: requires-dist
Dynamic: requires-python
Dynamic: summary
